{
    "$schema": "./../schema",
    "title": "邪神ちゃんドロップキック(1)",
    "release": [
        "2014-05-12",
        "2018-03-13"
    ],
    "isbn10": [
        "4593858070",
        "486675902X"
    ],
    "isbn13": [
        "978-4593858071",
        "978-4866759029"
    ],
    "asin": "B01EJ0879W",
    "body": [
        {
            "lines": [
                "ユキヲ",
                "初めましてユキヲと申します。連載から２年経ってやっと単行本になりました（笑）。これも応援してくださる皆様のおかげです。２巻、３巻と続けていければと思っていますのでこれからも邪神ちゃんの応援宜しくお願いします！"
            ]
        },
        {
            "episode": "0",
            "title": "召喚",
            "lines": [
                "ザザースザザースナスナザース",
                "この日 彼女「花園ゆりね」は",
                "古本屋で買った魔導書を手に悪魔召喚の儀式をゆるゆると行っていた…",
                "あこれくるかも何かくるかも",
                "カッ",
                "…あれここどこですの？",
                "お前が呼び出したんですの？",
                "邪の神「邪神ちゃん」",
                "…本物かしら？",
                "「お前」じゃなく私ゆりねっていうのよ",
                "今始めて会ったのに名前知ってるわけないだろ…",
                "で人間がなんの用ですの？",
                "…私 昔から黒魔術に興味があってね",
                "それで悪魔呼び出してみようかなって",
                "悪魔って本当にいたのね",
                "もう存在確認できたから帰っていいわよ",
                "なんだそれ…",
                "悪魔だって忙しいんだから用もないのに遊びで呼び出さないでほしいですの！",
                "悪かったわよ！早く帰んなさいよ！",
                "なんでこいつが怒ってんだ…？",
                "…じゃあ帰還の呪文で魔界に返してほしいですの",
                "帰還の呪文？",
                "知らないわよそんな呪文",
                "自分で勝手に帰ればいいじゃない",
                "呼び出した人間の呪文で帰るのが魔界のルールなんだよ！",
                "来たときだって勝手に来たわけじゃねーだろ",
                "たぶんその魔導書にも帰還の呪文が描いてあるはずですの",
                "えーと…",
                "なお召喚した悪魔を魔界に返す呪文については…",
                "下巻に続く…",
                "だって",
                "この本下巻あるんだ",
                "下巻あるんだじゃねぇだろ！！",
                "それがないと帰れないんですの！早く本屋行って下巻探してこーい！！",
                "それしか売ってなかったのよ",
                "そ そんな…",
                "他に帰る方法ないの？",
                "…呼び出された悪魔は人間界で活動中でも召喚者が死ぬと強制的に魔界に送り返されるんですの",
                "へー",
                "というわけで私は帰らせてもらう",
                "にやり…",
                "人間よ死ぬがよい！この必殺技のドロップキックで！！",
                "こうしてふたりの奇妙な生活と戦いの幕は切って落とされたのである！"
            ]
        },
        {
            "episode": "1",
            "title": "必殺のドロップキック",
            "lines": [
                "彼女は花園ゆりね",
                "地上最強の黒魔術師であり悪魔の医師を人々に伝える者",
                "そんな彼女は人々は恐れこう呼んでいる",
                "悪の伝道師黒のザビエル",
                "だがこれらは全て彼女の脳内設定だ",
                "ガチャガチャ",
                "リアルな彼女は黒魔術に悪魔学ホラー映画を好むちょっぴり残酷な心を持つただの女子大生",
                "ギィ",
                "だがつい先日のことーーー",
                "信じられないような出来事が起こった！",
                "なんと偶然 悪魔召喚に成功してしまったのだ",
                "おかえりなさいですの",
                "ただいま邪神ちゃん",
                "邪神ちゃんと呼ばれた存在がその悪魔だ",
                "下半身はヘビ（っていうかコブラ）そして上半身はギャル",
                "その姿はまさに悪魔誰が見てもあからさまに悪魔である！",
                "魔導書の下巻は見つかりましたの？",
                "学校の帰りに図書館で探してきたけどさっぱりだったわ",
                "ジャー",
                "バシャバシャ",
                "邪神のわたしが人間なんかと暮らさなければならないなんて…",
                "うっうっ",
                "私だって悪魔となんか暮らしたくないわよ",
                "……",
                "ならお望み通りぶっ殺して差し上げますわ！",
                "殺人ドロップキーック！！",
                "邪神ちゃんは特に凶暴な一面を見せ襲いかかる！！",
                "悪魔との生活は常に死と隣り合わせなのだ！",
                "ドカッ",
                "！！",
                "受け身",
                "パン！",
                "ドサッ…",
                "ねぇ死んだ？",
                "死にましたの？",
                "…また私のこと殺そうとしたわね…",
                "むく…",
                "！！？",
                "どうして！？どうしてきかないんですの必殺のドロップキックが！！",
                "なんのつもり？",
                "！！",
                "しょ…",
                "召喚者が死ねば強制的に魔界へ帰れるんだもん…",
                "魔導書見つかるまで待ってなさいってこないだ言ったよね…",
                "に…人間の指図は受けねぇですの！！",
                "あっそ",
                "スパッ",
                "！！",
                "ギャーしっぽが！！しっぽがー！！",
                "びちびち",
                "ゴロゴロゴロ",
                "あはは殺そうとした罰よ",
                "くぅ〜人間のくせに！人間のくせにぃ！！いつかぶっ殺し…",
                "あそういうこと言うんだ",
                "次はしっぽじゃなく胴体いくわよ",
                "いやーーー！！",
                "♫♫♪",
                "うるさいわね…隣の住人この前注意したのになんとかならないのかしら",
                "♬♪♪",
                "わ私がなんとかしてきますの！",
                "助かった…",
                "なんとかできるの？あんたに",
                "邪神のすごさを見せて差し上げますわ",
                "♪♫♫",
                "パタン",
                "♫♪",
                "ぴたっ…",
                "あ…静かになった",
                "静かになりましたの",
                "パタン",
                "わすごい血",
                "あんた何やったの？",
                "ご想像にお任せします",
                "ふーん",
                "まぁ 静かになればなんでもいいけどね",
                "この返り血を見ても顔色ひとつ変えないとは…",
                "それじゃ次はご飯の支度して",
                "悪魔使いの荒い人間ですの！！",
                "とりあえずシャワー浴びさせろーっ！",
                "さ電気代もったいないから寝るわよ",
                "はーい",
                "パチッ",
                "電気を消して油断したところを殺ってやりますの！",
                "そ〜…",
                "バカが！油断してんじゃねぇですの！",
                "ばっ",
                "ギャーーー！！",
                "バリバリバリバリ",
                "ううっ……魔除けの敷物の上に寝てやがる",
                "プスプス",
                "じわ",
                "くそっくそーっ！！",
                "ダンダン",
                "ぐーぐー",
                "邪神ちゃんとゆりねの奇妙な共同生活はまだ始まったばかりだ"
            ]
        },
        {
            "lines": [
                "おっ"
            ]
        },
        {
            "episode": "2",
            "title": "あずさ２号登場、そして死",
            "lines": [
                "へぇ…",
                "お姉さんが宇宙人と宇宙に…",
                "それは大変ね",
                "ええではまたオフ会の詳細が決まったら電話します",
                "それじゃあ",
                "ピッ",
                "まぁ…悪魔が呼び出せるんだから宇宙人がいても不思議じゃないけどね",
                "邪神ちゃんはおとなしくしてたかしら",
                "ガチャ",
                "ただいまー",
                "おかえりなさいですのーっ",
                "……",
                "どうしたのそれ…",
                "あずさ２号",
                "名前ではなくその不気味な生物をどうやって入手したか聞きたいんだけど",
                "大手通販サイトのアマゾネスで注文したペットの魔界バンビが届いたんですの",
                "アマゾネスって魔界の生物も届けてくれるんだ",
                "でもこのアパートペット禁止だから飼えないわよ返品しなさい",
                "えー",
                "こんなにかわいいのに返品だなんてカワイソウですの",
                "たしかにかわいいわね…",
                "でしょー",
                "フフフ…あずさ２号のかわいさにすっかり気を取られてますの",
                "そんな隙丸出しの貴様を殺し私は魔界へ帰る！",
                "カッ",
                "グッバイゆりね！！",
                "説明しよう邪神ちゃんが魔界へ帰るには召喚者のゆりねをｒｙ（長くなるので１話を参照）",
                "殺人ドロップキーック！",
                "サッ",
                "どがっ",
                "！！",
                "あずさ２号！！",
                "ぐら…",
                "ゴフ…",
                "……",
                "あーあー殺っちゃった",
                "ドサッ…",
                "てっ…てめぇが避けるからですの！",
                "あんたが私のこと殺そうとしたからでしょ",
                "あずさ２号が・・・・あずにゃんが死んでしまうとは…",
                "ううっ…",
                "スゥ…",
                "あずさ２号の魂が旅立っていきましたの…",
                "ふわ〜",
                "今が８時ちょうどだったら良かったのにね",
                "ピロリ〜ン♪",
                "あレベルが上がった",
                "邪神ちゃんのレベルが上がった",
                "ううっ…あずさ２号は経験値をいっぱい持っていたんですのね…",
                "レベル上がるんだ…",
                "あずさ２号が死んだのはゆりねのせいですの！！",
                "ばっ",
                "……",
                "なんとか言ったらどうですのゆりね！？",
                "あんた…私のこと指差したわね…",
                "そ…それがどうしたですの！？",
                "一番嫌なの…",
                "は…",
                "私指差されるのが一番嫌いなの…！！",
                "すっ…",
                "指差されたら刺しかえす",
                "サク",
                "ブシャア",
                "え",
                "ピャーーーーー！！！！！",
                "ぶしゅーーっ",
                "セーフなのは邪神ちゃんだけです。良い子は真似しないでね！",
                "傷口！傷口ふさがないと死ぬ！ア●ンアルファアロンア●ファはどこですのーっ",
                "わたわた",
                "ほらアロ●アルファ",
                "人のこと指差すからよ",
                "ふぅ…なんとかふさがったセーフですの…",
                "こ…こいつ指差したぐらいで刺すなんてとんでもねーキ●ガイですの",
                "魔界にだってこんなキ●ガイ滅多にいねぇぞ…",
                "チクショ〜こえ〜何者なんだよこいつはよ〜",
                "ねぇ",
                "ははい",
                "ところであずさ２号の代金はどうしたの？",
                "え…あ…後日 ゆりねの講座から引き落とされるかと…",
                "ふーん",
                "ホッ…怒ってない",
                "稼いで返しなさい",
                "へ…稼ぐ…？",
                "アンタ上半身は良い身体してるから結構稼げるかもね",
                "いやぁああぁあ！！"
            ]
        },
        {
            "lines": [
                "邪神ちゃんソーセージ",
                "４本入り",
                "シール付き",
                "ヘビ肉ソーセージ"
            ]
        },
        {
            "episode": "3",
            "title": "失われた本を求めて",
            "lines": [
                "Bondy",
                "カラーン…",
                "やばい…これはやばいですの…",
                "こんな美味しいカレーを出す店があったら他の店が潰れますの！",
                "店主を頃いてカレーを作るのやめさせないと…",
                "やめてよ",
                "がしっ",
                "この辺に住んでられなくなるでしょ",
                "チッ…",
                "はい舌打ちしない",
                "ぐさっ",
                "✗○□△？＝〒※〜！！",
                "ふー",
                "ふー",
                "おとなしくさっさと食べなさい",
                "あんたのためにこれから魔導書の下巻探しに行くんだからね",
                "間",
                "ここにもいないわね…",
                "悪魔学",
                "悪魔図鑑",
                "悪魔の食べ物",
                "あっ！悪魔図鑑だ",
                "私は載ってるかなー",
                "パラパラ",
                "悪魔図鑑〜これが魔界に住む悪魔の全て〜",
                "「全て」って書いてあるのに私が載ってないとはどういうことですの！",
                "あんた偉そうにしてるわりに図鑑に載らないようなマイナーな悪魔だったかー",
                "くっ…",
                "こんなもん売るんじゃねぇですの！",
                "お客さん売り物に困ります！",
                "バシッ",
                "うるせーこれタイトルが間違ってるだろうが！",
                "悪魔の全てじゃなく悪魔の一部だろうが！",
                "書き直せよ！！",
                "私著者じゃないんでそんなこと言われても…",
                "ぎゅううう",
                "やめなさいマイナーな悪魔",
                "この悪魔図鑑買います",
                "ぐったり",
                "…って気絶してるわ",
                "下巻見つからなかったわね",
                "ゆりねありがとう",
                "もういいですの",
                "にこっ",
                "どしたの急に",
                "最初から見つけるのなんて無理だったんですの",
                "COFEEE",
                "ちょっとでも期待しちゃった私バカな子",
                "探すなんてめんどくさいことはもうやめだ！！",
                "やっぱてめぇぶっ殺して帰ったほうが早いですのー！！",
                "死ねやードロップキーック！！",
                "シャー",
                "がっ",
                "え",
                "え",
                "ぐわっ",
                "えっ",
                "街中でそーいうことしたら…",
                "ぎゅん",
                "目立って恥ずかしいでしょ！！",
                "あー",
                "いっそこのまま魔界まで飛ばしてくれー",
                "なんだなんだ",
                "香",
                "うどん",
                "美味い！",
                "戻ってきた",
                "このうどん美味すぎる！",
                "店主殺してうどん作るのやめさせないと他の店が潰れますの！",
                "あんたどの店入ってもそれね",
            ]
        },
        {
            "lines": [
                "ぎゅっぎゅっ",
                "↑ぬか床",
            ]
        },
        {
            "episode": "4",
            "title": "第二の殺人技",
            "lines": [
                "ちょこん",
                "…また気味の悪い生き物がいるわね…",
                "単眼ちゃんですの",
                "何それ",
                "伝言用の下級悪魔ですの",
                "邪神様のレベルアップにより賞与が発生しましたのでお知らせします",
                "わーい",
                "やった〜！！",
                "それではこれで",
                "サッ",
                "どかーん",
                "爆発した…！？",
                "単願ちゃんは伝言を終えると自爆して死んでしまうんですの…",
                "なんと壮絶な…",
                "もくもく",
                "でもこのあとすぐ魔界で再生してワンランク上の悪魔として生まれ変わるんですのよ",
                "へー",
                "ところで邪神ちゃん",
                "前にもレベルアップとか言ってたけどレベル上がるとどうなるの？",
                "賞与が発生する他色々な特典がもらえますの",
                "特典？",
                "電車の無料チケットに…",
                "高級ホテルの宿泊券でしょーあと市ウーパーでの大幅割引券…",
                "まだまだ他にももらえますのよ！",
                "なにそれ株主優待券みたい",
                "っていうか魔界にスーパーあったんだ…",
                "これもあずさ２号のおかげですの",
                "じゃりがとうあずさ２号",
                "供物",
                "チョコレーツ",
                "アンハッピーターン",
                "あ〜魔界懐かしいなぁ",
                "ママやパパや友達のメデューサはどうしてるかな〜",
                "誰かさんが遊び半分で呼び出したせいで帰れなくなっちゃったからなー",
                "チラッチラッ",
                "勝手に帰っちゃえばいいのに",
                "魔界の掟は絶対ですの！",
                "人間に呼び出された悪魔は帰還の呪文で送り返してもらうか呼び出した人間が死ぬまで魔界へ帰ることは許されませんの…",
                "くすん",
                "自分の意志で人間界にやってきた悪魔は自由に帰れるのに呼び出された場合はダメなんてやっかいなルールね"…,,
                "そうなんですの…",
                "うっうっ",
                "…というわけで…",
                "チラッ",
                "死ねゆりね！！",
                "殺人ドロップキックと並ぶ第二の殺人技…ロイヤルコペンハーゲンによってな！！",
                "バッ",
                "ピタッ",
                "パン",
                "ガクン",
                "やるじゃない！",
                "ニコ！",
                "…また私のこと殺そうとしたわね…",
                "！！",
                "ビクゥ",
                "魔導書の下巻探すから待ってなさいって言ったわよね…",
                "ね",
                "は…はい…",
                "ガタガタ",
                "なんなんだよ〜こいつの願力",
                "人間のくせにあくまである私を一瞬で射すくめやがった…",
                "絶対はげる！こんなクレイジーな奴と暮らしてたらストレスで髪が抜けちまう…",
                "…ねぇ",
                "ははい！",
                "ビク",
                "さっきのロイヤルなんとかって何？",
                "ホッ話題がそれた…",
                "デンマークの陶磁器メーカーの名前ですの響きがカッコいいから拝借しましたの…",
                "ふ〜ん",
                "ドキドキ",
                "今日の夕飯なに？",
                "ビーフシチューをお作りしておきました…",
                "わ〜いビーフシチュー大好き",
                "ははは…",
                "そ…それは良かったですの"
            ]
        },
        {
            "episode": "5",
            "title": "彼女はメデューサちゃん（上）",
            "lines": [
                "秋葉原ー",
                "あの…",
                "道をお尋ねしたいのですが…",
                "ん？",
                "神保町へはどう行ったら…",
                "ぬふぉるふ！なにその可愛い声！",
                "俺の隙な声優にクリソツだし！なんでそんなの被ってんの！？",
                "顔見せたまえ",
                "えっ！？あ…顔は見ない方が…",
                "大丈夫大丈夫！声が可愛いと補正かかってたいしたことなくても可愛く見えちゃうから！",
                "ばっ",
                "あ…",
                "も…",
                "萌えぇぇー！！（死語）",
                "え…",
                "石化させちゃった…",
                "だから顔は見ない方がって言ったのに…",
                "くすん",
                "うぅっ…結局神保町どっちかわからなかった…",
                "ガササッ",
                "遅い！",
                "メデューサ遅いですの！",
                "うろうろ",
                "早くしないとゆりねが帰って来ちゃ…",
                "ピンポーン",
                "！",
                "もうっ！遅いですの！！",
                "ガチャ",
                "宅配便ですけど…",
                "あ…",
                "すみません…友人だと思ったもので…",
                "いえ…",
                "→ハンコ",
                "くぅ〜間違えてしまいましたの…",
                "はずかしーーーっ",
                "ピンポーン",
                "今度こそ…",
                "でも念のためのぞき穴から確認しますの…",
                "え…誰…？",
                "メデューサかな…？",
                "はっ",
                "そうだ！",
                "合言葉は…",
                "サンバのリズムで？",
                "カニバリズム",
                "ガチャ",
                "メデューサ",
                "邪神ちゃん！",
                "がっし",
                "さぁあがって",
                "お邪魔します",
                "はい砂糖入り麦茶",
                "コト",
                "ありがとう",
                "ところでその紙袋はなんですの？",
                "あ これ？人間が私の顔見ると石化しちゃうええしょ？それで被ってきたの",
                "魔物同士は石化しないんだからもう取って大丈夫ですの",
                "そそっか",
                "ふぅ…",
                "ガサ",
                "……",
                "うぅっ…",
                "なんですの…？急に泣いて",
                "ここに来る前に人間を一人石化しちゃったの…",
                "え？それがどうかしましたの？",
                "人間界は人口が多すぎますの",
                "一人減ったくらいなんてことないですの",
                "そんな…ひどい！",
                "悪魔みたいなこと言うなんて",
                "実際悪魔なんだよ",
                "…もう私悪魔やめたい",
                "仲良くしたいのに人間が私を見ると石化しちゃうんだもん…",
                "うっうっ…",
                "……",
                "しっかりしろメデューサ！！",
                "がっ",
                "これから私たちが戦うゆりねって人間はなーマジ半端ねぇんだぞ！！",
                "あいつの凶暴性についてはツイ●ターでＤＭしただろーっ！！",
                "人間と仲良くしたいとか甘いこと言ってんじゃねーよ！",
                "殺らなきゃ殺られちまうんだよーっ！！",
                "……",
                "ごめんね邪神ちゃん",
                "私しっかりする",
                "…私も取り乱して悪かったですの",
                "ゆりねさんってどれくらい強いの？",
                "ストⅡ初心者にとってのＣＰＵ戦７人目のブラ●カと同等の強さですの",
                "そんなに！",
                "だからメデューサの力が必要でわざわざ来てもらったんですの",
                "ぶるっ",
                "ああ…のんびりしていられないゆりねが帰ってきてしまう…",
                "で作戦だけども",
                "ゆりねが帰ってきたらメデューサが石化させる",
                "うん",
                "ピキーン",
                "そして私がドロップキックで粉々にする",
                "うん",
                "以上。",
                "さすがのゆりねも石化してからドロップキックを食らわせれば絶対に粉々になりますの",
                "恐ろしい作戦…",
                "あーやっと魔界に帰れる時がやってきましたの！",
                "これでゆりねもジ・エンドですの…",
                "ふっふっふっ…",
                "なんて恐ろしい顔してるのかしら邪神ちゃん…まさに邪神！！"
            ]
        },
        {
            "lines": [
                "メデューサの好物「砂糖入り麦茶」"
            ]
        },
        {
            "episode": "6",
            "title": "彼女はメデューサちゃん（下）",
            "lines": [
                "な…",
                "石化しないだと…？",
                "どうしたの邪神ちゃん？鳩が豆鉄砲を食ったような顔をして",
                "……",
                "うぷっ",
                "↗予想外の出来事に胃酸が上がってきた",
                "あ…あの",
                "どうしてあなたは石化しないんですか…？",
                "…邪神ちゃん",
                "思い出してごらん昨日の会話を",
                "え…",
                "ほわんほわん",
                "↗思い出す音",
                "パァン",
                "よろよろ",
                "↗ゾンビ",
                "あ゛〜〜",
                "ねぇゆりね",
                "なに",
                "魔界の友達が遊びに来たいって言ってるんだけど明日呼んでいいですの？",
                "好きにすれば",
                "良かったですの！ゆりねに紹介しますの",
                "じゃあ明日は早めに帰ってこないとね",
                "…ところで邪神ちゃん",
                "その子の名前なんて言うの？",
                "メデューサですの！",
                "メデューサですの！",
                "メデューサですの…",
                "（エコー）",
                "あ…！",
                "メデューサって名前から想像つくでしょ？その子が石化する能力を持ってることぐらい",
                "そこで石化防止のパワーストーンをアキバの露天商で買っておいたのよ",
                "バ…バカ言え！そんなアイテムが露店で売ってるわけ…",
                "それが売ってるんだなこの漫画の世界では",
                "どうせ私を石化してドロップキックで粉々にするとかそういうつもりだったんでしょ？",
                "すごい！全部当たってる",
                "メデューサお前はバカか！",
                "惜しかったわねぇ私に黙ってその子を呼べばうまくいったかもしれないのに",
                "……",
                "…う",
                "うをー！！それ以上近づいたらこの女の首をへし折って殺すぞ！",
                "ばっ",
                "！！",
                "つかつか",
                "バシン",
                "ブッ",
                "ぱっ",
                "…まったくあんたって子は",
                "ち…違いますの！この作戦はメデューサが考えたんですの！",
                "えっ",
                "そ…それで私は無理やり…",
                "邪神ちゃん卑怯すぎる…！",
                "ウソおっしゃい",
                "わかってるわね…",
                "くそー！！",
                "ポタポタ",
                "メデューサそいつを殺して私を助けろ！！",
                "助けられなくなっても助けろ！！",
                "切り込みを入れられ血を抜かれている",
                "血が…血がなくなっちまうー！！",
                "邪神ちゃんって昔から卑怯なの？",
                "はい…もう何千年も前からあんな感じです",
                "ああ…もうダメ…意識が遠くなってきた…",
                "こうして今回も邪神ちゃんの作戦は失敗に終わるのであった"
            ]
        },
        {
            "lines": [
                "わ…わかったしゃべる…"
            ]
        },
        {
            "episode": "7",
            "title": "マジカル★邪神ちゃん",
            "lines": [
                "むにゃむにゃ",
                "もう食べられねぇですのー",
                "はっ",
                "ゆりねのお弁当用意しないと…",
                "…って今日は日曜でしたの",
                "あれ…ゆりねがいない",
                "おでかけですの？",
                "キョロキョロ",
                "ん？",
                "絶対に変身しないで下さい",
                "……",
                "何ですのこれ…",
                "絶対に変身しないで…ってこんな玩具で変身できるわけありませんのー",
                "ゲラゲラゲラ",
                "ゆりねったらそんな置き手紙していかんでも最初から変身する気なんてないしー",
                "さー顔洗って朝ごはんたべよ",
                "くっふぅ〜〜",
                "辛いですの〜",
                "辛いというか痛いですのこのカレー",
                "めっちゃ汗出てきたこれは健康的な汗なの？それとも危険を知らせる汗なの？どっち？",
                "ぱくぱく",
                "しかし最近のレトルトカレーはおいしいなぁ",
                "……",
                "ちらっ…",
                "ごくり…",
                "まさかこのステッキ本当に変身できるんだろうか…？",
                "ま…興味ないけどねーっ",
                "さっ片づけよ",
                "ぺりっ",
                "朝ごはんも食べたし今度はおやつでも食べよう",
                "あーおいしいな〜ぷっ○んプリンはおいしいな〜",
                "昔スキャッドマンジロンがＣＭしてたな〜",
                "…",
                "ちらっ",
                "あのつまらないゆりねがこんなギャグみたいなことをやるだろうか…？",
                "だが石化防止のパワーストーンまで持ってたぐらいだぞ…ゆりねなら…",
                "変身☆",
                "いやまさか変身ステッキはないわな",
                "はは…",
                "……",
                "………",
                "我慢できませんのー！！",
                "がっ",
                "どうやるんですの？どうやるんですの？どうすれば変身するのですの！？",
                "変身☆",
                "サッ",
                "変身しませんの…",
                "はっ",
                "変身のためにはきっと呪文が必要なんですの！",
                "くぅ〜呪文さえわかれば〜！呪文さえわかれば〜！！",
                "ねぇ…なにやってんの",
                "ぴゃー ゆりね！！",
                "変身なんかしようとしてませんの！ただちょっと呪文がわからなかっただけで…",
                "呪文？ああそれね…",
                "「バカでーす☆」って言いながらかわいーポーズとるのよ",
                "そうすれば変身できるんですの！？",
                "やってみますの！",
                "バッカで〜す☆",
                "…あれ？",
                "変身しませんの…",
                "邪神ちゃん…あなた最高に面白い…",
                "えっ！？",
                "えっえっなになに？",
                "くっくっくっ…"
            ]
        },
        {
            "lines": [
                "パンケーキ"
            ]
        },
        {
            "episode": "8",
            "title": "邪神ちゃんと槍",
            "lines": [
                "ただいま",
                "おかえりなさ…",
                "！！",
                "そ…それなんですの？",
                "槍",
                "それは見ればわかりますの！",
                "なぜそんなものを持っているのかをきいてるんですの",
                "私ね…槍が大好きなの",
                "この槍で悪しき者を射つのよ！",
                "悪しき者？",
                "すっ…",
                "私の目の前にいる",
                "！",
                "……",
                "なーんてね",
                "フフフ…",
                "ゆりねの場合冗談に聞こえませんの…",
                "しかしこれホント良い槍ねぇ…",
                "こんなので刺されたらひとたまりもないわね",
                "た たのむ刺さないでくれ",
                "試し刺ししたいなぁ",
                "試すならやっぱり生物がいいわね",
                "人間や動物でもないけど生きているもの…どこかにいないかしら",
                "うぷっ",
                "それに該当するの私しかいませんの…！",
                "やー！",
                "ヒュ",
                "ピタッ",
                "ピャー！！！",
                "よろよろ",
                "どしん",
                "あわわ…",
                "ニヤリ",
                "ぷっ○んプリン食べよ",
                "……",
                "何が「やー！」だこのやろーふざけんなよ…！",
                "今ので確実に寿命が千年は縮んだぞ！",
                "やはりやられる前にやるしかねぇ…！",
                "ここのところ平和ボケしてましたの",
                "最近邪神ちゃんがドロップキックを使わないと思っている読者の諸君",
                "実はドロップキックは使わなければ使わないほどに威力が溜まっていくのだ",
                "パ○ソンのターンパンチのようにな！",
                "ゆりねは背を向けて無防備状態…",
                "今なら殺れる！",
                "すっ",
                "死ねーゆりねこれでジ エンドですのー！",
                "ファイナール！！",
                "シャー",
                "どしん",
                "あれ…？",
                "なんでですの…？",
                "はっ…",
                "ぷにーん",
                "しまったー！最近お菓子の食べすぎで太ったから重くなって飛距離が出ませんでしたのー！",
                "人間界のおかし うめぇ",
                "今何しようとしたの？",
                "え…あ…あの…",
                "すっ",
                "邪神ちゃん…",
                "ジ エンドね",
                "がばっ",
                "夢か…",
                "恐ろしい夢を見てしまいましたの…",
                "夢だけでも寿命が千年縮みましたの",
                "夢で良かったー",
                "ははは",
                "ただいま",
                "あー重かった",
                "…マジかよ"
            ]
        },
        {
            "episode": "9",
            "title": "バールのようなもの",
            "lines": [
                "頼んでおいたブツは持ってきてくれたんですの？",
                "うん",
                "これですの…！これを待っていたんですの！",
                "バール",
                "人間界の傷害事件ではよくバールのようなものが登場しますの…",
                "よく登場するってことはどういうことかわかるかメデューサ？",
                "えっ…",
                "人間に致命傷を与えるのに優れた武器ってことだよ！",
                "にやり…",
                "そしてこれは「バールのようなもの」ではなくバールそのもの…",
                "致命傷どころじゃすまねぇですの…",
                "これがあればゆりねをぶっ殺すことができる…！",
                "痛い！やめて許して！",
                "ダメだ！やめないし絶対に許さないですの！",
                "くっくっくっ…",
                "ゆりねの脳みそぶちまけてやりますの",
                "ガツンガツン",
                "脳みそ出ちゃってる",
                "ダメよ！そんなので殴ったらゆりねさん死んじゃうかも！",
                "かもじゃねぇよ殺すんだよ",
                "ああ…邪神ちゃんまるで悪魔だわ",
                "実際悪魔なんだよ",
                "フフフ…面白くなってきた",
                "うう…神様！どうか邪神ちゃんに天罰を！",
                "神に祈ってるけどこいつも悪魔",
                "ただいま",
                "おかえりなさいですの〜っ",
                "来てたんだ",
                "あ…はいお邪魔してます",
                "ゆりねの見たがったＤＶＤ買っておきましたの",
                "サッ",
                "へぇ…気がきくわね",
                "ゾンビもの",
                "ど〜ぞ見てくださいですの〜",
                "見てもいい？",
                "おかまいなく",
                "罠とも知らずいい気なもんだ",
                "ゆりねがＤＶＤに集中して油断してる間に脳天に一撃…",
                "これでジ・エンドですの",
                "アディオスゆりね！さぁ今日はサービスですの！",
                "読者の皆様に人間が脳みそぶちまけて死ぬところお見せして差し上げますわ！",
                "ぱしっ",
                "なっ…",
                "ぐぐっ",
                "ぱっ",
                "あ",
                "なぜバレた…",
                "あんた殴りかかるまでのセリフが長いのよ",
                "……",
                "メデューサ！またお前のせいで怒られるじゃねーか！",
                "ええっ！？",
                "がっ",
                "私は嫌だったんですのよ？でもメデューサに脅されて仕方なく…",
                "酷い…どうしてそんなウソつくの？",
                "てめぇメデューサ卑怯だぞ！私を罠にはめる気か！",
                "邪神ちゃん見苦しいわよ…",
                "わかってるわね？",
                "うぅ…助け…",
                "邪神ちゃんに再生能力があるからといってこれは酷すぎる…",
                "うぷっ",
                "ピッ",
                "さて…次回のお話までにモザイクがとれるぐらい邪神ちゃんは再生してるかしら…",
                "人間はどこまで残酷になれるのだろう…"
            ]
        },
        {
            "episode": "10",
            "title": "ゆりねワーキング",
            "lines": [
                "私が呼んだらすぐ来い私のメールには一分以内に返信しろ常に私を第一に考え優先しろ！",
                "う…うんそうする",
                "ぐつぐつ",
                "すき焼きおいしいですの〜♡",
                "ハナマサ秋葉原店まで肉を買いに行った甲斐がありましたの…",
                "野菜も食べなさい",
                "今まではすき焼きと言っても野菜と豆腐と春雨しか入ってなかったのに今日は肉がたくさん…",
                "だから野菜も食べなさい",
                "最近晩御飯が豪華ですの…",
                "何か悪いことでもしてるんですの？",
                "ゆりね貧乏でしょ？",
                "なんでそうなるのよ…",
                "バイト始めたの",
                "バイト何のバイトですの？",
                "バイトはバイトよ",
                "……",
                "ーー翌日",
                "ゆりねったら何のバイトしてるか全然教えてくれませんの…",
                "ガー",
                "人とかかわりたくない",
                "それ以前にゆりねが他の人間に混じって働いているところが全く想像できない…",
                "ゆりねのできそうなバイト…魔術",
                "カエル…トカゲ…",
                "いや…そんなバイトねーですの",
                "あーん気になりますの！",
                "ガー",
                "学校終わるころを見計らって後をつけてみますの",
                "キメラ大学",
                "来た…！",
                "こそっ",
                "御茶ノ水駅方面に歩いていきますの",
                "一体どこにいくのやら…",
                "おちゃのみずーおちゃのみずー",
                "お年寄りに席を譲りたくないから寝たフリしつつ様子を伺いますの",
                "チラッ",
                "優先席",
                "秋葉原ー秋葉原ー",
                "えっ もう降りるんですの？",
                "一駅！？一駅なのに乗ったの！？",
                "もったいない…たった一駅なら歩きますの…",
                "あのー無料でご覧になれますので個展見ていきませんか？",
                "なんだこいつ…",
                "見ませんの今忙しいんですの",
                "ホントちょっとでいいので",
                "うるさい人間ですの",
                "邪魔するとぶっ殺すぞゴミ！",
                "ひっ…",
                "びくっ",
                "す…すみませんでした",
                "ゴミが",
                "ふん",
                "…ってあれ！？ゆりねは！？",
                "くっふぅ〜〜",
                "ゴミのせいでゆりねを見失いましたの！",
                "仕方ない今日のところ諦めますの…",
                "神保町のミッキーよってゲームして帰ろう",
                "にゅるにゅる",
                "ヘビだ…",
                "CAFE 姫武者",
                "キィ…",
                "おはようございます",
                "ねぇ聞いてくださいよ！さっき下半身がヘビ女の子がいたんですよ",
                "そりゃそのぐらいいるでしょここ秋葉やし",
                "しかも上半身裸なんです",
                "そんなん全然普通でしょ〜だってここ秋葉やし",
                "え〜 珍しいですよねゆりねちゃん",
                "そうですね…",
                "帰ったらお仕置きが必要ね…"
            ]
        },
        {
            "lines": [
                "理想"
            ]
        },
        {
            "episode": "11",
            "title": "ウルトラハッピーバースデー",
            "lines": [
                "それじゃあ行ってきます",
                "帰ったらゆりねの誕生日を盛大にお祝いしますの",
                "メデューサと準備済ませとくのでお楽しみにー",
                "いってらっしゃいですの〜〜",
                "さてとメデューサが来るまでテレビでも見よう",
                "ピッ",
                "さそり座のあなた！今日のラッキーアイテムはスタンガンです！",
                "今日の星占い",
                "☆さそり座☆",
                "ラッキーアイテム",
                "スタンガン",
                "それでは良い一日をー",
                "今日の私のラッキーアイテムはスタンガンか…",
                "ヘビなのにさそり座",
                "…良いこと思いつきましたの",
                "メデューサにスタンガン持ってこさせよう",
                "ポテトチップスを持った手でさわる",
                "間",
                "はいゆりねさんのバースデーケーキと頼まれたモノ",
                "FUJIKE 不死家",
                "でかしたぞメデューサ",
                "ガサッ",
                "……",
                "何か悪いこと企んでるんでしょ？",
                "ニタァ…",
                "そうだよ〜",
                "やっぱり…！",
                "にこっ",
                "誕生日プレゼントを渡すフリをしてゆりねを油断させる…",
                "でやーっ",
                "ぎえー",
                "ビリビリ",
                "ヒャッハー",
                "で油断したところをスタンガンで行動不能にしたのち包丁で腹を掻っ捌いて殺す…",
                "もうドロップキックは使うのやめましたの",
                "それじゃこの漫画のタイトルが…",
                "…じゃあたまに使いますの",
                "この間のバールでの襲撃は失敗に終わったけど今回は絶対に上手くいきますの",
                "だって今日はラッキーアイテム補正付きだも〜ん",
                "失敗するわけありませんの",
                "ああ…なんて非道なのかしら",
                "人間の大切な記念日を利用するなんてゲスの極み！",
                "ただいまー",
                "バタン",
                "お帰りなさいゆりね！",
                "お祝いの準備できてますのー",
                "帰ってきたところ早速だけどプレゼントがありますのよ〜",
                "何かしら？",
                "今出しますの",
                "ガサ…",
                "ハッピーバースデーゆりね！",
                "私からのプレゼントは「死」ですのー！",
                "興奮で言葉になっていない",
                "オラァ下等生物が死ねＹ％Ω＄♪▽〜",
                "ヴィィィン…",
                "あれ…？",
                "電気シェーバー！？",
                "これヒゲ剃るやつですのー！！",
                "メデューサ！お前 私をはめたな！",
                "これスタンガンじゃなく電気シェーバーじゃねぇか！",
                "くぅふぅ〜中身を確認しておくべきだった！",
                "だって絶対悪いことに使うと思ったんだもの！",
                "私邪神ちゃんにこれ以上罪を重ねてほしくない！",
                "これ以上も何もまだ一度も罪を重ねてねーよ！アホかお前！",
                "こいつを殺れるチャンスだったんだぞ！",
                "へ",
                "ガッ",
                "ちょちょ",
                "なになになに",
                "コキャ",
                "あーー！！",
                "あ゛ーーーー",
                "ゴロゴロ",
                "…さっき私のこと下等生物って言ったわよね…",
                "ちょっとばかり人間様の言葉が理解できるからっていい気になるんじゃないわよ下等生物！",
                "わかってるわね？",
                "あ゛ーー！！",
                "ビッ",
                "叫んだいきおいで口角が切れた",
                "どう？本物のスタンガンの味は？",
                "あはは楽しい〜",
                "ビビビ",
                "な…なんでお前がスタンガンを…",
                "あ゛ーー！！",
                "メ…メデューサ早く助けろ気が狂っちまう…",
                "びくっびくっ",
                "ほら不死家のケーキよ食べなさい",
                "くっ…くえるか！！",
                "ゆりねさんの行動ってよくわからない…",
            ]
        },
        {
            "lines": [
                "石化だよ全員集合",
                "メデュ〜サ デビューシングル"
            ]
        },
        {
            "episode": "12",
            "title": "氷の悪魔・氷ちゃん来たる",
            "lines": [
                "暑い…",
                "人間界の夏ってやつは暑すぎますの…",
                "耐えなさい",
                "無理ですの…",
                "っていうかなんでこの部屋には冷たい風の出る機械がないんですの？",
                "ブオー",
                "エアコンのこと？そんなもの買えるわけないでしょ",
                "扇風機で耐えなさい",
                "こんな生ぬるい風で耐えられるか！",
                "…こうなったら魔界からアレを呼びますの",
                "…何この生き物",
                "氷の悪魔「氷ちゃん」ですの",
                "氷ちゃんがいるだけで部屋が涼しくなりますのよ",
                "じっ…",
                "おもしろい顔…",
                "そういえば涼しくなったわね…",
                "ひんやり…",
                "さらに",
                "さっ",
                "フッ",
                "サラサラ",
                "カキ氷も作ってくれるんですの",
                "へぇーすごい",
                "ちなみに氷ちゃんの血液がイチゴシロップ尿がレモンシロップになってますの",
                "どっちがいいですの？",
                "じゃあイチゴで",
                "サッ",
                "サクッ",
                "……",
                "あ…本当にイチゴシロップだわ…",
                "ぺろっ",
                "間",
                "ぼわっ",
                "こんな涼しい部屋でカキ氷まで食べられるなんてその子便利ねー",
                "ほっこり…",
                "他にこんなこともできますの",
                "さぁアレやって氷ちゃん",
                "ふるふる",
                "え？",
                "今はやりたくない？",
                "こくこく",
                "ふざけんじゃねぇですの",
                "生意気言ってないで",
                "さっさとやるんですの！",
                "……",
                "すっ…",
                "！",
                "部屋の中に雪が降ってきた",
                "ね〜すごいっしょ！",
                "下級悪魔にはこれくらい役に立ってもらわないとですの！",
                "ぴくっ…",
                "私のような上級悪魔に貢献できてうれしいっしょ〜",
                "…！",
                "キッ",
                "ん？ちょっと雪強くない？",
                "ぶるっ",
                "さむい…",
                "氷ちゃん…もうやめていいですの",
                "ヒュオオオオオオ",
                "ぷいっ",
                "もういいですの！",
                "ぶるるっ",
                "どんっ",
                "もういいって言ってんだよ！やめて帰れよ！！",
                "！",
                "……",
                "すっ…",
                "ちょっと邪神ちゃん！そんな言い方ないんじゃない？",
                "かわいそうよ",
                "ふーふー",
                "かわいそうなもんか",
                "コイツ下級悪魔のくせに邪神の私の言うこと聞かないなんて生意気ですの！",
                "パシ",
                "※邪神ちゃんは自分より小さくて弱そうな下級悪魔には容赦しないのだ！",
                "！",
                "がしっ",
                "パキッ",
                "な…凍らせやがった！",
                "このクソガキィィィィッ！",
                "ぐわっ",
                "フッ",
                "あ",
                "パキッ",
                "トン…",
                "パリーン",
                "ガシャン",
                "これ自己再生できるの？",
                "こくり"
            ]
        },
        {
            "episode": "13",
            "title": "メデューサちゃんレベルアップ",
            "lines": [
                "…なんですのその格好",
                "カッコイイでしょー",
                "レベルが上がって衣装が変わったんだよ",
                "…邪神ちゃん？",
                "くっふぅー",
                "悔しいですの！",
                "羨ましいですの！",
                "妬ましいですの！",
                "Ｋ・Ｕ・Ｎですの！！",
                "私もメデューサみたいなカッコイイ衣装が欲しいですの…",
                "しょんぼり…",
                "邪神ちゃんはレベルが上っても衣装変わらないの？",
                "変わるも何も最初からなんも着てないから変わりようがねぇですの…",
                "…カッコイイかどうかはわからないけど…",
                "これ着なさい",
                "買っちゃったけど色が合わなくてしまってあったの",
                "いつもゆりねが着てる服に似てますの",
                "でも私服着たことないから着方がわかりませんの…",
                "モニョモニョ",
                "しょうがないわね着せてやるか",
                "間",
                "…どうですの？",
                "カッコイイですの？",
                "邪神ちゃんかわいい〜！",
                "はい鏡",
                "に…人間の女みたいだ…",
                "これカッコイイですの！",
                "ありがとうですのゆりね！",
                "ふん…あんたにお礼を言われるなんてね…",
                "すごく喜んでる…",
                "良かったね邪神ちゃん！",
                "うん！",
                "でもメデューサが私より目立つカッコイイ衣装を着るのは許せないですの",
                "え…",
                "お前は私より出すぎるなレベルが上がってもまだお前のレベルは私の格下なんだからな！",
                "それをゆめゆめ忘れるな",
                "う…うん",
                "でお前今レベルいくつよ？",
                "５０だけど…",
                "うぷっ",
                "ぬ…抜かれてるじゃん…",
                "レベル４８",
                "黙っときゃわかんないから黙っとこー",
                "バシバシ",
                "そうか精進しろよメデューサ",
                "邪神ちゃんはレベルいくつなの",
                "うっ！！",
                "きゅ…急に具合が悪くなりましたの…",
                "はしゃぎすぎたからかな〜",
                "お先に寝ますの",
                "…",
                "パタン",
                "パン",
                "し知らない人が中にいますのー！",
                "魔女が一人に…",
                "悪魔が二匹…",
                "第２巻につづく"
            ]
        },
        {
            "episode": "番外編",
            "title": "邪神ちゃんは俺の嫁",
            "lines": [
                "コンコン",
                "入りなさい",
                "な…なんですのこの部屋？",
                "まっしろで何もない…",
                "ここは作者がピンチになると設置される下着のみにならないと入れない不思議な白い部屋よ",
                "そこにすわりなさい",
                "なんだそりゃ",
                "ねぇ邪神ちゃん今日あなたをここへ呼んだのはなぜだかわかる？",
                "え…",
                "ま…まさか！！",
                "机の引き出しにおにぎりを隠しておいたのがバレたんですの！？",
                "あとで食べよっと",
                "へぇ…隠してたんだ",
                "どうりで部屋から腐敗臭がすると思ったわ",
                "しまったー違ったのか！",
                "墓穴を掘ってしまった！！",
                "まぁその件はおいておくとして…",
                "邪神ちゃんこのあいだ",
                "私もアニメ化されて「邪神ちゃんは俺の嫁」とか言われたいですのーっ",
                "…って言ってたよね？",
                "い…言いましたの",
                "それが何か？",
                "本当にヲタク達に「嫁」とか言われたい？",
                "嫁なんて言われるのはアニメ放送中だけで終わったらすぐ別の作品のキャラを俺の嫁とか言い出すのよ",
                "そうねぇ…まぁもって三ヶ月ね",
                "！",
                "アニメ化されてヲタク達に嫁認定されちゃったらその時点であなたは余命三ヶ月のキャラになるのよ！",
                "それでもいいの！？",
                "ビシイ",
                "え…あ…ぅ…",
                "ああ…同人作家がこぞってあなたの薄い本を作り一時だけ邪神ちゃんの本ばかりが専門書店の本棚に並ぶのが目に浮かぶわ…",
                "邪神ちゃんドロップキック作品コーナー",
                "邪神ちゃんと…",
                "ですの",
                "ー邪ー",
                "で数カ月後には別の人気キャラの薄い本がその棚を埋めてるっていうね…",
                "あぁあぁ",
                "注目のタグ",
                "邪神ちゃんドロップキック",
                "イラスト投稿サイトでも一時だけ邪神ちゃんのイラストが増えて旬が過ぎたらさんざんネタにしたくせにオワコンとか言われちゃうのよ",
                "くくっ",
                "うぷっ",
                "それからねぇ…",
                "やめてぇーっ！！",
                "ぶわわっ",
                "もうやめてほしいですの！！",
                "嫁になんかならなくていいですのーっ！",
                "うっうっ",
                "……",
                "わかったらもう二度と嫁って言われたいなんて思わないことね",
                "こくこくこく",
                "でもアニメ化はしてほしいわね",
                "どっち！？",
            ]
        },
        {
            "lines": [
                "邪神ちゃんの食器"
            ]
        },
        {
            "title": "おまけまんが",
            "lines": [
                "これいいでしょモーニングスター",
                "買ったのよ",
                "へ〜…",
                "あら？",
                "道が崩れてる…",
                "これじゃ渡れないわね",
                "飛び越えますの",
                "無理よあんたと違ってそんな運動能力ないもの",
                "橋…",
                "何か橋のようなものないかなー",
                "ないかなー",
                "ちらっ",
                "ヒュンヒュン",
                "……",
                "あからさまに私にやれってことですの…",
                "やらなきゃあれで殺られる…！",
                "やーー！！",
                "ばっ",
                "がっ",
                "は…早く渡りますの！",
                "あらあんた気が利くわね",
                "ぎゅっぎゅっ",
                "くっ！",
                "よいしょ",
                "！？",
                "お泣かすいちゃったお弁当食べましょっと",
                "キ●ガイかこいつ！早く渡れー！！",
                "もう漫画終わるわよ言うことあるでしょ",
                "に…二巻もよろしくですの…"
            ]
        },
        {
            "lines": [
                "おにぎりがみっつ…",
                "布団の上に食べ物置くなって言ったでしょ！！",
                "びく"
            ]
        },
        {
            "lines": [
                "ボロアパート（六畳間）で邪神とふたり",
                "You must eat vegetable.",
                "Yes, me'em"
            ]
        },
        {
            "lines": [
                "喰らえ必殺のドロップキック"
            ]
        }
    ]
}
